notebook_vis_cli/__init__.py
notebook_vis_cli/__main__.py
notebook_vis_cli-0.1.1.dist-info/METADATA
notebook_vis_cli-0.1.1.dist-info/WHEEL
notebook_vis_cli-0.1.1.dist-info/entry_points.txt
notebook_vis_cli-0.1.1.dist-info/RECORD
