Metadata-Version: 2.1
Name: notebook-vis-cli
Version: 0.1.1
Summary: Generate jupyter notebooks preloaded with visualization boilerplate
Author: Ben Skubi
Author-email: bskubi@gmail.com
Requires-Python: >=3.12,<4.0
Classifier: Programming Language :: Python :: 3
Classifier: Programming Language :: Python :: 3.12
Requires-Dist: click (>=8.1.7,<9.0.0)
Requires-Dist: nbformat (>=5.9.2,<6.0.0)
Requires-Dist: pandas (>=2.2.0,<3.0.0)
Requires-Dist: pyyaml (>=6.0.1,<7.0.0)
Requires-Dist: seaborn (>=0.13.2,<0.14.0)
